pspylib/__init__.py
pspylib/ars/__init__.py
pspylib/ars/defines.py
pspylib/ars/frame.py
pspylib/ars/reader.py
pspylib/ars/table.py
pspylib/ars/tools.py
pspylib/ppt/__init__.py
pspylib/ppt/defines.py
pspylib/ppt/frame.py
pspylib/ppt/reader.py
pspylib/ppt/table.py
pspylib/ppt/tools.py
pspylib/tiff/__init__.py
pspylib/tiff/constant.py
pspylib/tiff/imageViewer.py
pspylib/tiff/metaData.py
pspylib/tiff/reader.py
pspylib/tiff/tools.py
pspylib/tiff/writer.py
pspylib/utils/__init__.py
pspylib/utils/types.py
pspylib-0.1.2.dist-info/LICENSE.txt
pspylib-0.1.2.dist-info/METADATA
pspylib-0.1.2.dist-info/WHEEL
pspylib-0.1.2.dist-info/top_level.txt
pspylib-0.1.2.dist-info/RECORD
