Metadata-Version: 2.1
Name: pspylib
Version: 0.1.2
Summary: Park Systems Python library for SPM
Home-page: https://www.parksystems.com
Author: Park Systems
Author-email: rsw@parksystems.com
License: UNKNOWN
Keywords: park,systems,spm,afm
Platform: UNKNOWN
Requires-Python: >=3
